simple_knn/__init__.py
eden_simple_knn-0.1.0a0.dist-info/METADATA
eden_simple_knn-0.1.0a0.dist-info/WHEEL
eden_simple_knn-0.1.0a0.dist-info/top_level.txt
eden_simple_knn-0.1.0a0.dist-info/RECORD
