Metadata-Version: 2.4
Name: eden_simple_knn
Version: 0.1.0a0
Summary: Simple KNN CUDA implementation for 3D Gaussian Splatting
Home-page: https://github.com/Kashu7100/simple-knn/
Author: Kashu Yamazaki
Requires-Python: >=3.7
Requires-Dist: torch>=1.13.0
Requires-Dist: ninja
Dynamic: author
Dynamic: description
Dynamic: description-content-type
Dynamic: home-page
Dynamic: requires-dist
Dynamic: requires-python
Dynamic: summary
